tests/__init__.py
tests/test_erd.py
graphviz_erd-0.0.0.dist-info/LICENSE
graphviz_erd-0.0.0.dist-info/METADATA
graphviz_erd-0.0.0.dist-info/WHEEL
graphviz_erd-0.0.0.dist-info/top_level.txt
graphviz_erd-0.0.0.dist-info/RECORD
