Metadata-Version: 2.1
Name: graphviz-erd
Version: 0.0.0
Summary: Draw Entity-Relationship Diagrams (ERD) with python.
Home-page: https://github.com/mashi/graphviz-erd
Author: mashi
Author-email: 59000162+mashi@users.noreply.github.com
License: UNKNOWN
Project-URL: Bug Tracker, https://github.com/mashi/graphviz-erd/issues
Platform: UNKNOWN
Classifier: Programming Language :: Python :: 3
Classifier: License :: OSI Approved :: MIT License
Classifier: Operating System :: OS Independent
Requires-Python: >=3.7
License-File: LICENSE
Requires-Dist: graphviz (~=0.19.1)
